client/__init__.py
client/cli.py
client/schemas.py
stride_gpt_cli-0.1.2.dist-info/LICENSE
stride_gpt_cli-0.1.2.dist-info/METADATA
stride_gpt_cli-0.1.2.dist-info/WHEEL
stride_gpt_cli-0.1.2.dist-info/entry_points.txt
stride_gpt_cli-0.1.2.dist-info/top_level.txt
stride_gpt_cli-0.1.2.dist-info/RECORD
